{
  "todos": [
    {
      "content": "Sunucu durumunu ve bağlantısını kontrol et",
      "id": "1",
      "status": "in_progress"
    },
    {
      "content": "WhatsApp client bağlantısını doğrula",
      "id": "2",
      "status": "pending"
    },
    {
      "content": "Mesaj event'lerinin tetiklenip tetiklenmediğini kontrol et",
      "id": "3",
      "status": "pending"
    },
    {
      "content": "Bot trigger mantığını test et",
      "id": "4",
      "status": "pending"
    },
    {
      "content": "Debug modu ekle ve detaylı loglama yap",
      "id": "5",
      "status": "pending"
    },
    {
      "content": "Gerçek sorunu bul ve düzelt",
      "id": "6",
      "status": "pending"
    }
  ],
  "sessionId": "45a40a89-3ca1-470f-850b-15a7958e46ed"
}